AUTHORS
COPYING
MANIFEST.in
README
build.sh
ez_setup.py
gen-doc-api.sh
setup.cfg
setup.py
evas/__init__.py
evas/debug.py
evas/decorators.py
evas/evas.c_evas.c
evas/evas.c_evas.h
evas/evas.c_evas.pyx
evas/evas.c_evas_canvas.pxi
evas/evas.c_evas_canvas_callbacks.pxi
evas/evas.c_evas_object.pxi
evas/evas.c_evas_object_box.pxi
evas/evas.c_evas_object_callbacks.pxi
evas/evas.c_evas_object_events.pxi
evas/evas.c_evas_object_image.pxi
evas/evas.c_evas_object_line.pxi
evas/evas.c_evas_object_polygon.pxi
evas/evas.c_evas_object_rectangle.pxi
evas/evas.c_evas_object_smart.pxi
evas/evas.c_evas_object_text.pxi
evas/evas.c_evas_object_textblock.pxi
evas/evas.c_evas_rect.pxi
evas/evas_object_image_mask.c
evas/evas_object_image_rotate.c
evas/utils.py
examples/01-smart_object.py
include/evas/__init__.py
include/evas/c_evas.pxd
include/evas/evas_object_image_python_extras.h
python_evas.egg-info/PKG-INFO
python_evas.egg-info/SOURCES.txt
python_evas.egg-info/dependency_links.txt
python_evas.egg-info/not-zip-safe
python_evas.egg-info/top_level.txt
tests/01-canvas-basics.py
tests/02-object-basics.py
tests/03-rect.py
tests/04-object-image.py
tests/05-smart-object.py
tests/06-canvas-as-factory.py
tests/07-smart_object-as-factory.py
tests/08-object-polygon.py
tests/10-object_text.py
tests/11-decorators.py
tests/12-image_as_buffer.py
tests/13-image-rotate.py
tests/14-image-preload.py
tests/icon.png